morse_audio/__init__.py
morse_audio/morse.py
morse_audio-0.1.0.dist-info/licenses/LICENSE
morse_audio-0.1.0.dist-info/METADATA
morse_audio-0.1.0.dist-info/WHEEL
morse_audio-0.1.0.dist-info/top_level.txt
morse_audio-0.1.0.dist-info/RECORD
