Metadata-Version: 2.4
Name: morse_audio
Version: 0.1.0
Summary: Python library for Morse code conversion and audio generation
Home-page: https://github.com/MattiaAlessi/Morse
Author: Mattia Alessi
Classifier: Programming Language :: Python :: 3
Classifier: License :: OSI Approved :: MIT License
Classifier: Operating System :: OS Independent
Requires-Python: >=3.8
License-File: LICENSE
Requires-Dist: numpy
Requires-Dist: sounddevice
Dynamic: license-file
